shephex/__init__.py
shephex/where.py
shephex/cli/__init__.py
shephex/cli/execute.py
shephex/cli/main.py
shephex/cli/report.py
shephex/cli/slurm/__init__.py
shephex/cli/slurm/add_info.py
shephex/cli/slurm/cancel.py
shephex/cli/slurm/open.py
shephex/cli/slurm/profile.py
shephex/cli/slurm/slurm.py
shephex/cli/study/__init__.py
shephex/cli/study/build.py
shephex/cli/study/main.py
shephex/decorators/__init__.py
shephex/decorators/chain.py
shephex/decorators/hexperiment.py
shephex/executor/__init__.py
shephex/executor/executor.py
shephex/executor/slurm/__init__.py
shephex/executor/slurm/functional.py
shephex/executor/slurm/slurm_body.py
shephex/executor/slurm/slurm_executor.py
shephex/executor/slurm/slurm_header.py
shephex/executor/slurm/slurm_options.py
shephex/executor/slurm/slurm_profile.py
shephex/executor/slurm/slurm_script.py
shephex/experiment/__init__.py
shephex/experiment/chain_iterator.py
shephex/experiment/context.py
shephex/experiment/experiment.py
shephex/experiment/meta.py
shephex/experiment/options.py
shephex/experiment/result.py
shephex/experiment/status.py
shephex/experiment/procedure/__init__.py
shephex/experiment/procedure/pickle.py
shephex/experiment/procedure/procedure.py
shephex/experiment/procedure/script.py
shephex/study/__init__.py
shephex/study/renderer.py
shephex/study/study.py
shephex/study/table/__init__.py
shephex/study/table/littletable_table.py
shephex-0.3.2.dist-info/METADATA
shephex-0.3.2.dist-info/WHEEL
shephex-0.3.2.dist-info/entry_points.txt
shephex-0.3.2.dist-info/licenses/LICENSE
shephex-0.3.2.dist-info/RECORD
