Metadata-Version: 2.4
Name: shephex
Version: 0.3.2
Summary: Computational experiment manager. Execute parameterized Python function on Slurm directly from a python script
License-File: LICENSE
Requires-Python: >=3.11
Requires-Dist: click>=8.2.0
Requires-Dist: dill>=0.3.8
Requires-Dist: littletable>=3.0.0
Requires-Dist: numpy<2
Requires-Dist: rich-click>=1.8.9
Requires-Dist: rich>=13.7.1
Requires-Dist: shortuuid>=1.0.13
